{
  "/api/auth/me/route": "app/api/auth/me/route.js",
  "/api/invoices/[id]/route": "app/api/invoices/[id]/route.js",
  "/api/notifications/route": "app/api/notifications/route.js",
  "/api/dashboard/route": "app/api/dashboard/route.js",
  "/api/invoices/route": "app/api/invoices/route.js",
  "/api/pos/menu/route": "app/api/pos/menu/route.js",
  "/page": "app/page.js",
  "/pos/restaurant/page": "app/pos/restaurant/page.js",
  "/room-status/page": "app/room-status/page.js",
  "/calendar/page": "app/calendar/page.js",
  "/invoice/restaurant/page": "app/invoice/restaurant/page.js"
}